winipedia_utils/__init__.py
winipedia_utils/dev/__init__.py
winipedia_utils/dev/artifacts/__init__.py
winipedia_utils/dev/artifacts/build.py
winipedia_utils/dev/artifacts/builder/__init__.py
winipedia_utils/dev/artifacts/builder/base/__init__.py
winipedia_utils/dev/artifacts/builder/base/base.py
winipedia_utils/dev/artifacts/builder/builder.py
winipedia_utils/dev/cli/__init__.py
winipedia_utils/dev/cli/cli.py
winipedia_utils/dev/cli/subcommands.py
winipedia_utils/dev/cli/winipedia_utils_cli.py
winipedia_utils/dev/configs/__init__.py
winipedia_utils/dev/configs/base/__init__.py
winipedia_utils/dev/configs/base/base.py
winipedia_utils/dev/configs/builder.py
winipedia_utils/dev/configs/configs.py
winipedia_utils/dev/configs/conftest.py
winipedia_utils/dev/configs/dot_env.py
winipedia_utils/dev/configs/dot_python_version.py
winipedia_utils/dev/configs/experiment.py
winipedia_utils/dev/configs/gitignore.py
winipedia_utils/dev/configs/licence.py
winipedia_utils/dev/configs/pre_commit.py
winipedia_utils/dev/configs/py_typed.py
winipedia_utils/dev/configs/pyproject.py
winipedia_utils/dev/configs/readme.py
winipedia_utils/dev/configs/subcommands.py
winipedia_utils/dev/configs/workflows/__init__.py
winipedia_utils/dev/configs/workflows/base/__init__.py
winipedia_utils/dev/configs/workflows/base/base.py
winipedia_utils/dev/configs/workflows/health_check.py
winipedia_utils/dev/configs/workflows/publish.py
winipedia_utils/dev/configs/workflows/release.py
winipedia_utils/dev/configs/zero_test.py
winipedia_utils/dev/git/__init__.py
winipedia_utils/dev/git/github/__init__.py
winipedia_utils/dev/git/github/github.py
winipedia_utils/dev/git/github/repo/__init__.py
winipedia_utils/dev/git/github/repo/protect.py
winipedia_utils/dev/projects/__init__.py
winipedia_utils/dev/projects/create_root.py
winipedia_utils/dev/projects/poetry/__init__.py
winipedia_utils/dev/projects/poetry/dev_deps.py
winipedia_utils/dev/projects/poetry/poetry.py
winipedia_utils/dev/projects/poetry/versions.py
winipedia_utils-0.7.32.dist-info/METADATA
winipedia_utils-0.7.32.dist-info/WHEEL
winipedia_utils-0.7.32.dist-info/entry_points.txt
winipedia_utils-0.7.32.dist-info/licenses/LICENSE
winipedia_utils-0.7.32.dist-info/RECORD
