Metadata-Version: 2.4
Name: winipedia-utils
Version: 0.7.32
Summary: A package with many utility functions
License-Expression: MIT
License-File: LICENSE
Author: Winipedia
Author-email: win.steveker@gmx.de
Requires-Python: >=3.12
Classifier: Programming Language :: Python :: 3
Classifier: Programming Language :: Python :: 3.12
Classifier: Programming Language :: Python :: 3.13
Classifier: Programming Language :: Python :: 3.14
Requires-Dist: bandit
Requires-Dist: cryptography
Requires-Dist: defusedxml
Requires-Dist: dotenv
Requires-Dist: keyring
Requires-Dist: mypy
Requires-Dist: networkx
Requires-Dist: packaging
Requires-Dist: pathspec
Requires-Dist: pillow
Requires-Dist: polars
Requires-Dist: pre-commit
Requires-Dist: pygithub
Requires-Dist: pytest
Requires-Dist: pytest-mock
Requires-Dist: pyyaml
Requires-Dist: ruff
Requires-Dist: setuptools
Requires-Dist: tomlkit
Requires-Dist: tqdm
Requires-Dist: typer
Requires-Dist: types-defusedxml
Requires-Dist: types-networkx
Requires-Dist: types-pyyaml
Requires-Dist: types-setuptools
Requires-Dist: types-tqdm
